starviewshare/__init__.py
starviewshare/stock/__init__.py
starviewshare-0.1.2.dist-info/LICENSE
starviewshare-0.1.2.dist-info/METADATA
starviewshare-0.1.2.dist-info/WHEEL
starviewshare-0.1.2.dist-info/top_level.txt
starviewshare-0.1.2.dist-info/RECORD
