Metadata-Version: 2.1
Name: starviewshare
Version: 0.1.2
Summary: A finance tool to get stock,fund and futures data
Home-page: https://github.com/rchardzhu/starviewshare
Author: Richard Zhu
Author-email: rchardzhu@gmail.com
License: MIT
Project-URL: Documentation, https://github.com/rchardzhu/starviewshare
Project-URL: Source, https://github.com/rchardzhu/starviewshare
Keywords: finance,quant,stock,etf,futures,starviewshare
Platform: any
Classifier: License :: OSI Approved :: MIT License
Classifier: Programming Language :: Python :: 3.8
Classifier: Programming Language :: Python :: 3.9
Classifier: Programming Language :: Python :: 3.10
Classifier: Programming Language :: Python :: 3.11
Requires-Python: >=3.8
License-File: LICENSE
Requires-Dist: requests
Requires-Dist: pandas
Requires-Dist: tqdm
Requires-Dist: efinance
